sonad/__init__.py
sonad/cli.py
sonad/config.py
sonad/core.py
sonad/CZI/synonyms_matrix.csv
sonad/json/candidate_urls.json
sonad/json/metadata_cache.json
sonad/json/synonym_dictionary.json
sonad/model.pkl
sonad/models.py
sonad/preprocessing.py
sonad-0.2.6.dist-info/entry_points.txt
sonad-0.2.6.dist-info/LICENSE
sonad-0.2.6.dist-info/METADATA
sonad-0.2.6.dist-info/WHEEL
sonad-0.2.6.dist-info/RECORD
