Metadata-Version: 2.3
Name: sonad
Version: 0.2.6
Summary: Software name disambiguation pipeline
License: MIT
Keywords: software,disambiguation,metadata,machine learning,NLP
Author: Jelena Duric
Author-email: djuricjelena611@gmail.com
Requires-Python: >=3.10,<=3.13
Classifier: Development Status :: 3 - Alpha
Classifier: Intended Audience :: Science/Research
Classifier: License :: OSI Approved :: MIT License
Classifier: Programming Language :: Python :: 3
Classifier: Programming Language :: Python :: 3.10
Classifier: Programming Language :: Python :: 3.11
Classifier: Programming Language :: Python :: 3.12
Classifier: Programming Language :: Python :: 3.13
Classifier: Topic :: Scientific/Engineering :: Artificial Intelligence
Classifier: Topic :: Software Development :: Libraries :: Python Modules
Requires-Dist: SPARQLWrapper (>=1.8,<2.0)
Requires-Dist: beautifulsoup4 (>=4.9)
Requires-Dist: click (>=8.0,<9.0)
Requires-Dist: cloudpickle (>=2.0)
Requires-Dist: lightgbm (>=3.3)
Requires-Dist: rdflib (>=6.0.1)
Requires-Dist: sentence-transformers (>=2.2)
Requires-Dist: somef (>=0.9.11)
Requires-Dist: textdistance (>=4.2)
Requires-Dist: xgboost (>=1.5)
Project-URL: Homepage, https://github.com/jelenadjuric01/Software-Disambiguation
Project-URL: Repository, https://github.com/jelenadjuric01/Software-Disambiguation
